Workbook

Sheet Data
A1: Invoice ID | B1: Purchase Date | C1: Day of Purchase | D1: Time of Purchase | E1: Full Name | F1: Age | G1: Age Segment | H1: Gender | I1: City | J1: Product | K1: Category | L1: Quantity | M1: Unit Price | N1: Total Sales | O1: Discount (%) | P1: Discount | Q1: Total Sales After Discount | R1: Loyalty Points Earned | S1: Payment Method | T1: Department
A2: INV-100000 | B2: 45597 | C2: Friday | D2: 21:45:45 | E2: Linda Morrison | F2: 28 | G2: {=_xlfn.IFS(F2<12,"Child",F2<18,"Teen",F2<25,"Young",F2<40,"Adult",F2<60,"Middle Age",F2>=60,"Old")} -> Adult | H2: Male | I2: Mansoura | J2: Jacket | K2: =VLOOKUP(J2,Sheet2!$A$1:$B$11,2,FALSE) -> Winter Wear | L2: 1 | M2: 201 | N2: 201 | O2: 0.15 | P2: =N2*O2 -> 30.15 | Q2: =N2-P2 -> 170.85 | R2: 3 | S2: E-Wallet | T2: Men
A3: INV-100001 | B3: 45704 | C3: Sunday | D3: 23:41:36 | E3: Gregory Cummings | F3: 39 | G3: {=_xlfn.IFS(F3<12,"Child",F3<18,"Teen",F3<25,"Young",F3<40,"Adult",F3<60,"Middle Age",F3>=60,"Old")} -> Adult | H3: Male | I3: Hurghada | J3: Pants | K3: =VLOOKUP(J3,Sheet2!$A$1:$B$11,2,FALSE) -> Casual Wear | L3: 4 | M3: 1093 | N3: 4372 | O3: 0.1 | P3: =N3*O3 -> 437.2 | Q3: =N3-P3 -> 3934.8 | R3: 78 | S3: E-Wallet | T3: Women
A4: INV-100002 | B4: 45607 | C4: Monday | D4: 13:12:42 | E4: Julie Williams | F4: 54 | G4: {=_xlfn.IFS(F4<12,"Child",F4<18,"Teen",F4<25,"Young",F4<40,"Adult",F4<60,"Middle Age",F4>=60,"Old")} -> Middle Age | H4: Female | I4: Alexandria | J4: Sweatshirt | K4: =VLOOKUP(J4,Sheet2!$A$1:$B$11,2,FALSE) -> Sportswear | L4: 2 | M4: 852 | N4: 1704 | O4: 0 | P4: =N4*O4 -> 0 | Q4: =N4-P4 -> 1704 | R4: 34 | S4: Cash | T4: Kids
A5: INV-100003 | B5: 45632 | C5: Friday | D5: 07:25:54 | E5: Anita Wallace | F5: 60 | G5: {=_xlfn.IFS(F5<12,"Child",F5<18,"Teen",F5<25,"Young",F5<40,"Adult",F5<60,"Middle Age",F5>=60,"Old")} -> Old | H5: Female | I5: Alexandria | J5: Suit | K5: =VLOOKUP(J5,Sheet2!$A$1:$B$11,2,FALSE) -> Formal Wear | L5: 3 | M5: 1194 | N5: 3582 | O5: 0.1 | P5: =N5*O5 -> 358.2 | Q5: =N5-P5 -> 3223.8 | R5: 64 | S5: E-Wallet | T5: Kids
A6: INV-100005 | B6: 45516 | C6: Monday | D6: 23:04:43 | E6: Monica Wilson | F6: 42 | G6: {=_xlfn.IFS(F6<12,"Child",F6<18,"Teen",F6<25,"Young",F6<40,"Adult",F6<60,"Middle Age",F6>=60,"Old")} -> Middle Age | H6: Female | I6: Mansoura | J6: Shorts | K6: =VLOOKUP(J6,Sheet2!$A$1:$B$11,2,FALSE) -> Summer Wear | L6: 1 | M6: 488 | N6: 488 | O6: 0.05 | P6: =N6*O6 -> 24.4 | Q6: =N6-P6 -> 463.6 | R6: 9 | S6: Visa | T6: Women
A7: INV-100006 | B7: 45623 | C7: Wednesday | D7: 17:29:48 | E7: Johnny Gill | F7: 40 | G7: {=_xlfn.IFS(F7<12,"Child",F7<18,"Teen",F7<25,"Young",F7<40,"Adult",F7<60,"Middle Age",F7>=60,"Old")} -> Middle Age | H7: Female | I7: Port Said | J7: T-Shirt | K7: =VLOOKUP(J7,Sheet2!$A$1:$B$11,2,FALSE) -> Casual Wear | L7: 5 | M7: 787 | N7: 3935 | O7: 0.15 | P7: =N7*O7 -> 590.25 | Q7: =N7-P7 -> 3344.75 | R7: 66 | S7: Visa | T7: Women
A8: INV-100007 | B8: 45547 | C8: Thursday | D8: 14:35:41 | E8: Debra Zuniga | F8: 19 | G8: {=_xlfn.IFS(F8<12,"Child",F8<18,"Teen",F8<25,"Young",F8<40,"Adult",F8<60,"Middle Age",F8>=60,"Old")} -> Young | H8: Male | I8: Cairo | J8: Sneakers | K8: =VLOOKUP(J8,Sheet2!$A$1:$B$11,2,FALSE) -> Sportswear | L8: 3 | M8: 165 | N8: 495 | O8: 0.05 | P8: =N8*O8 -> 24.75 | Q8: =N8-P8 -> 470.25 | R8: 9 | S8: Cash | T8: Kids
A9: INV-100008 | B9: 45713 | C9: Tuesday | D9: 09:46:12 | E9: Christopher Burch | F9: 53 | G9: {=_xlfn.IFS(F9<12,"Child",F9<18,"Teen",F9<25,"Young",F9<40,"Adult",F9<60,"Middle Age",F9>=60,"Old")} -> Middle Age | H9: Female | I9: Port Said | J9: Jacket | K9: =VLOOKUP(J9,Sheet2!$A$1:$B$11,2,FALSE) -> Winter Wear | L9: 4 | M9: 693 | N9: 2772 | O9: 0.1 | P9: =N9*O9 -> 277.2 | Q9: =N9-P9 -> 2494.8 | R9: 49 | S9: Visa | T9: Men
A10: INV-100009 | B10: 45437 | C10: Saturday | D10: 12:08:38 | E10: Michael Sims | F10: 18 | G10: {=_xlfn.IFS(F10<12,"Child",F10<18,"Teen",F10<25,"Young",F10<40,"Adult",F10<60,"Middle Age",F10>=60,"Old")} -> Young | H10: Male | I10: Luxor | J10: T-Shirt | K10: =VLOOKUP(J10,Sheet2!$A$1:$B$11,2,FALSE) -> Casual Wear | L10: 3 | M10: 1158 | N10: 3474 | O10: 0.05 | P10: =N10*O10 -> 173.7 | Q10: =N10-P10 -> 3300.3 | R10: 66 | S10: Cash | T10: Women
A11: INV-100010 | B11: 45525 | C11: Wednesday | D11: 06:46:51 | E11: Dylan Saunders | F11: 31 | G11: {=_xlfn.IFS(F11<12,"Child",F11<18,"Teen",F11<25,"Young",F11<40,"Adult",F11<60,"Middle Age",F11>=60,"Old")} -> Adult | H11: Female | I11: Tanta | J11: Classic Shoes | K11: =VLOOKUP(J11,Sheet2!$A$1:$B$11,2,FALSE) -> Formal Wear | L11: 5 | M11: 222 | N11: 1110 | O11: 0.1 | P11: =N11*O11 -> 111 | Q11: =N11-P11 -> 999 | R11: 19 | S11: E-Wallet | T11: Women
A12: INV-100011 | B12: 45559 | C12: Tuesday | D12: 03:52:47 | E12: Krystal Smith | F12: 46 | G12: {=_xlfn.IFS(F12<12,"Child",F12<18,"Teen",F12<25,"Young",F12<40,"Adult",F12<60,"Middle Age",F12>=60,"Old")} -> Middle Age | H12: Male | I12: Hurghada | J12: Sweatshirt | K12: =VLOOKUP(J12,Sheet2!$A$1:$B$11,2,FALSE) -> Sportswear | L12: 5 | M12: 279 | N12: 1395 | O12: 0.1 | P12: =N12*O12 -> 139.5 | Q12: =N12-P12 -> 1255.5 | R12: 25 | S12: Visa | T12: Men
A13: INV-100012 | B13: 45613 | C13: Sunday | D13: 23:27:46 | E13: Sherri Tran | F13: 48 | G13: {=_xlfn.IFS(F13<12,"Child",F13<18,"Teen",F13<25,"Young",F13<40,"Adult",F13<60,"Middle Age",F13>=60,"Old")} -> Middle Age | H13: Female | I13: Cairo | J13: Sweatshirt | K13: =VLOOKUP(J13,Sheet2!$A$1:$B$11,2,FALSE) -> Sportswear | L13: 1 | M13: 342 | N13: 342 | O13: 0.1 | P13: =N13*O13 -> 34.2 | Q13: =N13-P13 -> 307.8 | R13: 6 | S13: Cash | T13: Kids
... A1005: INV-101004 | B1005: 45488 | C1005: Saturday | D1005: 19:41:14 | E1005: Laura Jones | F1005: 59 | G1005: {=_xlfn.IFS(F1005<12,"Child",F1005<18,"Teen",F1005<25,"Young",F1005<40,"Adult",F1005<60,"Middle Age",F1005>=60,"Old")} -> Middle Age | H1005: Female | I1005: Tanta | J1005: T-Shirt | K1005: =VLOOKUP(J1005,Sheet2!$A$1:$B$11,2,FALSE) -> Casual Wear | L1005: 1 | M1005: 933 | N1005: 933 | O1005: 0.15 | P1005: =N1005*O1005 -> 139.95 | Q1005: =N1005-P1005 -> 793.05 | R1005: 63 | S1005: Cash | T1005: Women

Sheet Sheet2
A1: Product | B1: Category
A2: T-Shirt | B2: Casual Wear
A3: Shirt | B3: Formal Wear
A4: Pants | B4: Casual Wear
A5: Jacket | B5: Winter Wear
A6: Shorts | B6: Summer Wear
A7: Sweatshirt | B7: Sportswear
A8: Suit | B8: Formal Wear
A9: Sneakers | B9: Sportswear
A10: Classic Shoes | B10: Formal Wear
A11: Accessories | B11: Fashion Accessories
